MANIFEST.in
serdaripsum.py
setup.py
data/songs.txt
serdaripsum.egg-info/PKG-INFO
serdaripsum.egg-info/SOURCES.txt
serdaripsum.egg-info/dependency_links.txt
serdaripsum.egg-info/not-zip-safe
serdaripsum.egg-info/requires.txt
serdaripsum.egg-info/top_level.txt