Metadata-Version: 1.0
Name: serdaripsum
Version: 1.6
Summary: serdar ipsum generator that runs on bash.
Home-page: https://github.com/halilkaya/serdaripsum
Author: Halil Kaya
Author-email: kayahalil@gmail.com
License: GPLv3
Platform: UNKNOWN
